cose/__init__.py
cose/algorithms.py
cose/exceptions.py
cose/headers.py
cose/utils.py
cose/extensions/__init__.py
cose/extensions/x509.py
cose/keys/__init__.py
cose/keys/cosekey.py
cose/keys/curves.py
cose/keys/ec2.py
cose/keys/keyops.py
cose/keys/keyparam.py
cose/keys/keytype.py
cose/keys/okp.py
cose/keys/rsa.py
cose/keys/symmetric.py
cose/messages/__init__.py
cose/messages/context.py
cose/messages/cosebase.py
cose/messages/cosemessage.py
cose/messages/enc0message.py
cose/messages/enccommon.py
cose/messages/encmessage.py
cose/messages/mac0message.py
cose/messages/maccommon.py
cose/messages/macmessage.py
cose/messages/recipient.py
cose/messages/sign1message.py
cose/messages/signcommon.py
cose/messages/signer.py
cose/messages/signmessage.py
cose-0.9.dev8.dist-info/LICENSE
cose-0.9.dev8.dist-info/METADATA
cose-0.9.dev8.dist-info/WHEEL
cose-0.9.dev8.dist-info/top_level.txt
cose-0.9.dev8.dist-info/RECORD
