Metadata-Version: 2.1
Name: cose
Version: 0.9.dev8
Summary: CBOR Object Signing and Encryption (COSE) implementation
Home-page: https://pycose.readthedocs.io/en/latest/
Author: Timothy Claeys
Author-email: timothy.claeys@gmail.com
License: BSD-3
Keywords: COSE,Internet of Things,CBOR,object security,EDHOC,OSCORE,cryptography
Platform: platform-independent
Classifier: Development Status :: 3 - Alpha
Classifier: Intended Audience :: Developers
Classifier: Topic :: Internet
Classifier: Topic :: Communications
Classifier: Topic :: Software Development
Classifier: Topic :: System :: Networking
Classifier: License :: OSI Approved :: BSD License
Classifier: Programming Language :: Python :: 3
Classifier: Programming Language :: Python :: 3.6
Classifier: Programming Language :: Python :: 3.7
Classifier: Programming Language :: Python :: 3.8
Requires-Python: >=3.6
License-File: LICENSE
